__init__.py
flurry/__init__.py
flurry/systems/__init__.py
flurry/systems/host.py
flurry/systems/scada.py
flurry/systems/science.py
flurry/systems/sdn.py
flurry/systems/user.py
flurry/systems/web.py
flurry-0.1.1.dist-info/LICENSE
flurry-0.1.1.dist-info/METADATA
flurry-0.1.1.dist-info/WHEEL
flurry-0.1.1.dist-info/top_level.txt
flurry-0.1.1.dist-info/RECORD
