Metadata-Version: 2.1
Name: flurry
Version: 0.1.1
Summary: Cyber attack and benign behavior automation for systems designed for data provenance capture
Author-email: Maya Kapoor <mkapoor1@uncc.edu>
License: MIT License        
Project-URL: Homepage, https://github.com/mayakapoor/flurry
Classifier: Programming Language :: Python :: 3
Classifier: License :: OSI Approved :: MIT License
Classifier: Operating System :: OS Independent
Requires-Python: >=3.7
License-File: LICENSE
